git_commit_generator/__init__.py
git_commit_generator/cli/__init__.py
git_commit_generator/cli/file_selector.py
git_commit_generator/cli/main.py
git_commit_generator/cli/ui_utils.py
git_commit_generator/config.py
git_commit_generator/core.py
git_commit_generator/git_operations.py
git_commit_generator/models/.provider.json
git_commit_generator/models/__init__.py
git_commit_generator/models/adapter.py
git_commit_generator/models/provider.py
git_commit_generator/validators.py
quick_auto_git-0.1.4.dist-info/METADATA
quick_auto_git-0.1.4.dist-info/WHEEL
quick_auto_git-0.1.4.dist-info/entry_points.txt
quick_auto_git-0.1.4.dist-info/licenses/LICENSE
quick_auto_git-0.1.4.dist-info/RECORD
